mate3/api.py
mate3/devices.py
mate3/field_values.py
mate3/main.py
mate3/modbus_client.py
mate3/read.py
mate3/sunspec/doc/AXS_APP_NOTE.pdf
mate3/sunspec/doc/OutBack.Power.SunSpec.Map.xlsx
mate3/sunspec/doc/SunSpec-Information-Models-12041.pdf
mate3/sunspec/fields.py
mate3/sunspec/model_base.py
mate3/sunspec/models.py
mate3/sunspec/scripts/code_generator.py
mate3/sunspec/values.py
mate3/tests/known_systems/chinezbrun/expected.json
mate3/tests/known_systems/chinezbrun/modbus.json
mate3/tests/test_cli.py
mate3/tests/test_io.py
mate3/tests/test_known_systems.py
mate3-0.6.2.dist-info/entry_points.txt
mate3-0.6.2.dist-info/LICENSE
mate3-0.6.2.dist-info/WHEEL
mate3-0.6.2.dist-info/METADATA
mate3-0.6.2.dist-info/RECORD
