Metadata-Version: 2.1
Name: mate3
Version: 0.6.2
Summary: Outback Mate3s Python Library
Home-page: https://github.com/adamcharnock/mate3/
Author: Adam Charnock
Author-email: adam@adamcharnock.com
Requires-Python: >=3.7,<4.0
Classifier: Programming Language :: Python :: 3
Classifier: Programming Language :: Python :: 3.7
Classifier: Programming Language :: Python :: 3.8
Classifier: Programming Language :: Python :: 3.9
Requires-Dist: fixedint (>=0.1.6,<0.2.0)
Requires-Dist: loguru (>=0.5.3,<0.6.0)
Requires-Dist: pymodbus (>=2.4,<3.0)
Project-URL: Repository, https://github.com/adamcharnock/mate3/
